setup.py
./__init__.py
./address_book.py
./chats.py
./message.py
./utils/__init__.py
./utils/sqlite.py
pymessage.egg-info/PKG-INFO
pymessage.egg-info/SOURCES.txt
pymessage.egg-info/dependency_links.txt
pymessage.egg-info/top_level.txt
utils/sqlite.py