Metadata-Version: 1.0
Name: pymessage
Version: 0.1.3
Summary: Python library for reading and managing Apple iMessage database
Home-page: https://github.com/mjbrisebois/pymessage
Author: Matthew Brisebois
Author-email: matthew@webheroes.ca
License: UNKNOWN
Keywords: pymessage,imessage
Platform: UNKNOWN
